sqlite_memory_vfs.py
sqlite_memory_vfs-0.0.14.dist-info/METADATA
sqlite_memory_vfs-0.0.14.dist-info/WHEEL
sqlite_memory_vfs-0.0.14.dist-info/licenses/LICENSE
sqlite_memory_vfs-0.0.14.dist-info/RECORD
