Metadata-Version: 2.1
Name: sqlite-memory-vfs
Version: 0.0.14
Summary: Python writable in-memory virtual filesystem for SQLite
Project-URL: Homepage, https://github.com/michalc/sqlite-memory-vfs
Author-email: Michal Charemza <michal@charemza.name>, Department for International Trade <sre@digital.trade.gov.uk>
License-File: LICENSE
Classifier: License :: OSI Approved :: MIT License
Classifier: Programming Language :: Python :: 3
Classifier: Topic :: Database
Requires-Python: >=3.7.11
Requires-Dist: apsw>=3.43.0.0
Requires-Dist: sortedcontainers>=2.4.0
Provides-Extra: dev
Requires-Dist: pytest-cov>=3.0.0; extra == 'dev'
Requires-Dist: pytest>=6.2.5; extra == 'dev'
